hpe_warranty_lookup/__init__.py
hpe_warranty_lookup/hpe_warranty_lookup.py
hpe_warranty_lookup-0.2.2.dist-info/METADATA
hpe_warranty_lookup-0.2.2.dist-info/WHEEL
hpe_warranty_lookup-0.2.2.dist-info/entry_points.txt
hpe_warranty_lookup-0.2.2.dist-info/top_level.txt
hpe_warranty_lookup-0.2.2.dist-info/RECORD
